gacha_elper/__init__.py
gacha_elper/adb/__init__.py
gacha_elper/adb/adb.py
gacha_elper/elper/__init__.py
gacha_elper/elper/coordinate.py
gacha_elper/elper/elper.py
gacha_elper-1.1.0.dist-info/LICENSE
gacha_elper-1.1.0.dist-info/METADATA
gacha_elper-1.1.0.dist-info/WHEEL
gacha_elper-1.1.0.dist-info/top_level.txt
gacha_elper-1.1.0.dist-info/RECORD
